hyperon_das/__init__.py
hyperon_das/api.py
hyperon_das/das.py
hyperon_das/exceptions.py
hyperon_das/factory.py
hyperon_das/logger.py
hyperon_das/pattern_matcher/__init__.py
hyperon_das/pattern_matcher/constants.py
hyperon_das/pattern_matcher/pattern_matcher.py
test_publish_gwgwrhw-0.1.6.dist-info/METADATA
test_publish_gwgwrhw-0.1.6.dist-info/WHEEL
test_publish_gwgwrhw-0.1.6.dist-info/RECORD
