Metadata-Version: 2.1
Name: test-publish-gwgwrhw
Version: 0.1.6
Summary: Query Engine API for Distributed AtomSpace
Author: marcocapozzoli
Author-email: marcocapozzoli90@gmail.com
Requires-Python: >=3.8.5,<4.0.0
Classifier: Programming Language :: Python :: 3
Classifier: Programming Language :: Python :: 3.9
Classifier: Programming Language :: Python :: 3.10
Classifier: Programming Language :: Python :: 3.11
Requires-Dist: hyperon-das-atomdb (>=0.1.7,<0.2.0)
